{
  "timestamp": "2025-05-29 07:02:18",
  "type": "current",
  "data": {
    "coord": {
      "lon": -58.5796,
      "lat": -34.426
    },
    "weather": [
      {
        "id": 800,
        "main": "Clear",
        "description": "clear sky",
        "icon": "01n"
      }
    ],
    "base": "stations",
    "main": {
      "temp": 5.45,
      "feels_like": 3.38,
      "temp_min": 4.55,
      "temp_max": 7.34,
      "pressure": 1025,
      "humidity": 81,
      "sea_level": 1025,
      "grnd_level": 1024
    },
    "visibility": 10000,
    "wind": {
      "speed": 2.57,
      "deg": 220
    },
    "clouds": {
      "all": 0
    },
    "dt": 1748502138,
    "sys": {
      "type": 1,
      "id": 8232,
      "country": "AR",
      "sunrise": 1748515839,
      "sunset": 1748551992
    },
    "timezone": -10800,
    "id": 3427761,
    "name": "Tigre",
    "cod": 200
  }
}