{
  "timestamp": "2025-05-09 07:01:52",
  "type": "current",
  "data": {
    "coord": {
      "lon": -58.5796,
      "lat": -34.426
    },
    "weather": [
      {
        "id": 802,
        "main": "Clouds",
        "description": "scattered clouds",
        "icon": "03n"
      }
    ],
    "base": "stations",
    "main": {
      "temp": 15.54,
      "feels_like": 15.58,
      "temp_min": 14.56,
      "temp_max": 16.23,
      "pressure": 1010,
      "humidity": 93,
      "sea_level": 1010,
      "grnd_level": 1008
    },
    "visibility": 10000,
    "wind": {
      "speed": 3.13,
      "deg": 171,
      "gust": 4.92
    },
    "clouds": {
      "all": 40
    },
    "dt": 1746773912,
    "sys": {
      "type": 1,
      "id": 8232,
      "country": "AR",
      "sunrise": 1746786973,
      "sunset": 1746824719
    },
    "timezone": -10800,
    "id": 3427761,
    "name": "Tigre",
    "cod": 200
  }
}