{
  "timestamp": "2025-08-07 07:02:18",
  "type": "current",
  "data": {
    "coord": {
      "lon": -58.5796,
      "lat": -34.426
    },
    "weather": [
      {
        "id": 800,
        "main": "Clear",
        "description": "clear sky",
        "icon": "01n"
      }
    ],
    "base": "stations",
    "main": {
      "temp": 10.47,
      "feels_like": 9.69,
      "temp_min": 9.06,
      "temp_max": 10.97,
      "pressure": 1023,
      "humidity": 81,
      "sea_level": 1023,
      "grnd_level": 1021
    },
    "visibility": 10000,
    "wind": {
      "speed": 2.06,
      "deg": 210
    },
    "clouds": {
      "all": 0
    },
    "dt": 1754550137,
    "sys": {
      "type": 1,
      "id": 8232,
      "country": "AR",
      "sunrise": 1754563328,
      "sunset": 1754601482
    },
    "timezone": -10800,
    "id": 3427761,
    "name": "Tigre",
    "cod": 200
  }
}