{
  "timestamp": "2025-05-06 07:02:12",
  "type": "current",
  "data": {
    "coord": {
      "lon": -58.5796,
      "lat": -34.426
    },
    "weather": [
      {
        "id": 802,
        "main": "Clouds",
        "description": "scattered clouds",
        "icon": "03n"
      }
    ],
    "base": "stations",
    "main": {
      "temp": 18.49,
      "feels_like": 18.9,
      "temp_min": 17.89,
      "temp_max": 19,
      "pressure": 1015,
      "humidity": 96,
      "sea_level": 1015,
      "grnd_level": 1013
    },
    "visibility": 10000,
    "wind": {
      "speed": 3.09,
      "deg": 100
    },
    "clouds": {
      "all": 40
    },
    "dt": 1746514670,
    "sys": {
      "type": 1,
      "id": 8232,
      "country": "AR",
      "sunrise": 1746527632,
      "sunset": 1746565675
    },
    "timezone": -10800,
    "id": 3427761,
    "name": "Tigre",
    "cod": 200
  }
}